xileh/__init__.py
xileh/core/__init__.py
xileh/core/pipeline.py
xileh/core/pipelinedata.py
xileh/lib/__init__.py
xileh/lib/signal/__init__.py
xileh/lib/signal/filter.py
xileh/utils/__init__.py
xileh/utils/logger.py
xileh/utils/monitoring.py
xileh/utils/nemo_eval.py
xileh/utils/datahandler/__init__.py
xileh/utils/datahandler/loading.py
xileh/utils/datahandler/saving.py
xileh-0.0.1.dist-info/LICENSE.txt
xileh-0.0.1.dist-info/METADATA
xileh-0.0.1.dist-info/WHEEL
xileh-0.0.1.dist-info/top_level.txt
xileh-0.0.1.dist-info/RECORD
