Metadata-Version: 2.1
Name: xileh
Version: 0.0.1
Summary: A pipeline abstraction tool helping you organise and reuse processing pipelines
Author-email: Matthias Dold <matthias.dold@gmx.net>
Classifier: Programming Language :: Python :: 3
Classifier: License :: OSI Approved :: MIT License
Classifier: Operating System :: OS Independent
Requires-Python: >=3.6
License-File: LICENSE.txt
Requires-Dist: pandas (>=1.5)
Requires-Dist: pyyaml (>=6)
Requires-Dist: tqdm (>=4.64)
Requires-Dist: toml (>=0.10)
